benfordslaw/__init__.py
benfordslaw/benfordslaw.py
benfordslaw/examples.py
benfordslaw-2.1.0.dist-info/licenses/LICENSE
benfordslaw-2.1.0.dist-info/METADATA
benfordslaw-2.1.0.dist-info/WHEEL
benfordslaw-2.1.0.dist-info/top_level.txt
benfordslaw-2.1.0.dist-info/RECORD
