Metadata-Version: 2.4
Name: benfordslaw
Version: 2.1.0
Summary: benfordslaw is a python library to test the frequency distribution of leading digits.
Author-email: Erdogan Taskesen <erdogant@gmail.com>
License-Expression: MIT
Project-URL: Homepage, https://erdogant.github.io/benfordslaw
Project-URL: Download, https://github.com/erdogant/benfordslaw/archive/{version}.tar.gz
Keywords: Python,benfordslaw,statistical analysis,Fraud detection,data validation
Classifier: Programming Language :: Python :: 3
Classifier: Intended Audience :: Education
Classifier: Intended Audience :: Science/Research
Classifier: Operating System :: Unix
Classifier: Operating System :: Microsoft :: Windows
Classifier: Operating System :: MacOS
Classifier: Operating System :: OS Independent
Classifier: Topic :: Scientific/Engineering :: Artificial Intelligence
Requires-Python: >=3
License-File: LICENSE
Requires-Dist: matplotlib
Requires-Dist: numpy
Requires-Dist: scipy
Requires-Dist: pandas
Requires-Dist: datazets>=0.2.0
Dynamic: license-file
